[
  {
    "username": "userb",
    "firstname": "b",
    "lastname": "bb",
    "email": "bb@gmail.com",
    "password": "U2FsdGVkX1+Fy6qLZEwdqAUZab8x9XjOpn8aRjJ8yls=",
    "id": "69539"
  },
  {
    "username": "m",
    "firstname": "m",
    "lastname": "m",
    "email": "m@m.com",
    "password": "U2FsdGVkX1+esiHCX3wnKo2NewedOPdVIT8w4k6aVOM=",
    "id": "10610"
  },
  {
    "username": "t",
    "firstname": "t",
    "lastname": "t",
    "email": "t@t.com",
    "password": "U2FsdGVkX18dL2iPqFRFDEnOBfSDXamYP2sob7MPUDs=",
    "id": "65202",
    "subscribe": true
  }
]